{
  "jsonSchemaSemanticVersion": "1.0.0",
  "manifestName": "Miscellaneous",
  "entities": [
    {
      "type": "LocalEntity",
      "entityName": "PurchPurchaseOrderHeader",
      "entityPath": "PurchPurchaseOrderHeader.cdm.json/PurchPurchaseOrderHeader"
    },
    {
      "type": "LocalEntity",
      "entityName": "ProcCategoryTmpAccessPolicy",
      "entityPath": "ProcCategoryTmpAccessPolicy.cdm.json/ProcCategoryTmpAccessPolicy"
    },
    {
      "type": "LocalEntity",
      "entityName": "PurchReqTableMyRequisitionsDataSetTable",
      "entityPath": "PurchReqTableMyRequisitionsDataSetTable.cdm.json/PurchReqTableMyRequisitionsDataSetTable"
    },
    {
      "type": "LocalEntity",
      "entityName": "PurchAgreementCertification",
      "entityPath": "PurchAgreementCertification.cdm.json/PurchAgreementCertification"
    },
    {
      "type": "LocalEntity",
      "entityName": "PurchaseOrderResponseActionRemarks",
      "entityPath": "PurchaseOrderResponseActionRemarks.cdm.json/PurchaseOrderResponseActionRemarks"
    },
    {
      "type": "LocalEntity",
      "entityName": "PurchReceiptsListHeaderTmp",
      "entityPath": "PurchReceiptsListHeaderTmp.cdm.json/PurchReceiptsListHeaderTmp"
    },
    {
      "type": "LocalEntity",
      "entityName": "PurchRFQPublishLine_PSN",
      "entityPath": "PurchRFQPublishLine_PSN.cdm.json/PurchRFQPublishLine_PSN"
    },
    {
      "type": "LocalEntity",
      "entityName": "PurchRFQCaseTableKMCollection",
      "entityPath": "PurchRFQCaseTableKMCollection.cdm.json/PurchRFQCaseTableKMCollection"
    },
    {
      "type": "LocalEntity",
      "entityName": "PurchAgreementSubcontractor",
      "entityPath": "PurchAgreementSubcontractor.cdm.json/PurchAgreementSubcontractor"
    },
    {
      "type": "LocalEntity",
      "entityName": "PurchPolicyRuleCatThreshold_PSN",
      "entityPath": "PurchPolicyRuleCatThreshold_PSN.cdm.json/PurchPolicyRuleCatThreshold_PSN"
    },
    {
      "type": "LocalEntity",
      "entityName": "PurchReApprovalPolicyRuleFields",
      "entityPath": "PurchReApprovalPolicyRuleFields.cdm.json/PurchReApprovalPolicyRuleFields"
    },
    {
      "type": "LocalEntity",
      "entityName": "PurchRFQSolicitationType",
      "entityPath": "PurchRFQSolicitationType.cdm.json/PurchRFQSolicitationType"
    },
    {
      "type": "LocalEntity",
      "entityName": "PurchRFQTableKMCollection",
      "entityPath": "PurchRFQTableKMCollection.cdm.json/PurchRFQTableKMCollection"
    },
    {
      "type": "LocalEntity",
      "entityName": "PurchPurchaseOrderTmp",
      "entityPath": "PurchPurchaseOrderTmp.cdm.json/PurchPurchaseOrderTmp"
    },
    {
      "type": "LocalEntity",
      "entityName": "VendRFQAmendmentJour",
      "entityPath": "VendRFQAmendmentJour.cdm.json/VendRFQAmendmentJour"
    },
    {
      "type": "LocalEntity",
      "entityName": "PurchRFQTableQuestionnaireResponse",
      "entityPath": "PurchRFQTableQuestionnaireResponse.cdm.json/PurchRFQTableQuestionnaireResponse"
    },
    {
      "type": "LocalEntity",
      "entityName": "PurchRFQReplyScoringStatus",
      "entityPath": "PurchRFQReplyScoringStatus.cdm.json/PurchRFQReplyScoringStatus"
    },
    {
      "type": "LocalEntity",
      "entityName": "PurchRFQCloseVisibilityType_PSN",
      "entityPath": "PurchRFQCloseVisibilityType_PSN.cdm.json/PurchRFQCloseVisibilityType_PSN"
    },
    {
      "type": "LocalEntity",
      "entityName": "PurchReqTableHistoryTotals",
      "entityPath": "PurchReqTableHistoryTotals.cdm.json/PurchReqTableHistoryTotals"
    },
    {
      "type": "LocalEntity",
      "entityName": "PurchAgreementFinDimensionAccess_PSN",
      "entityPath": "PurchAgreementFinDimensionAccess_PSN.cdm.json/PurchAgreementFinDimensionAccess_PSN"
    },
    {
      "type": "LocalEntity",
      "entityName": "PurchPolicyRuleCatThresholdDetail_PSN",
      "entityPath": "PurchPolicyRuleCatThresholdDetail_PSN.cdm.json/PurchPolicyRuleCatThresholdDetail_PSN"
    },
    {
      "type": "LocalEntity",
      "entityName": "AifPortValueMap",
      "entityPath": "AifPortValueMap.cdm.json/AifPortValueMap"
    },
    {
      "type": "LocalEntity",
      "entityName": "PurchReceiptsListDetailsTmp",
      "entityPath": "PurchReceiptsListDetailsTmp.cdm.json/PurchReceiptsListDetailsTmp"
    },
    {
      "type": "LocalEntity",
      "entityName": "PSNPurchRFQSolicitationBiddingItem",
      "entityPath": "PSNPurchRFQSolicitationBiddingItem.cdm.json/PSNPurchRFQSolicitationBiddingItem"
    },
    {
      "type": "LocalEntity",
      "entityName": "PSNPurchRFQBiddingGuidanceItem",
      "entityPath": "PSNPurchRFQBiddingGuidanceItem.cdm.json/PSNPurchRFQBiddingGuidanceItem"
    },
    {
      "type": "LocalEntity",
      "entityName": "PSNPurchRFQCaseBiddingGuidanceItem",
      "entityPath": "PSNPurchRFQCaseBiddingGuidanceItem.cdm.json/PSNPurchRFQCaseBiddingGuidanceItem"
    }
  ],
  "relationships": [
    {
      "name": "",
      "fromEntity": "PurchPurchaseOrderHeader.cdm.json/PurchPurchaseOrderHeader",
      "fromEntityAttribute": "Relationship_CompanyCurrencyRelationshipId",
      "toEntity": "/core/operationsCommon/Tables/Common/Currency/Group/Currency.cdm.json/Currency",
      "toEntityAttribute": "RecId"
    },
    {
      "name": "",
      "fromEntity": "PurchPurchaseOrderHeader.cdm.json/PurchPurchaseOrderHeader",
      "fromEntityAttribute": "Relationship_CurrencyRelationshipId",
      "toEntity": "/core/operationsCommon/Tables/Common/Currency/Group/Currency.cdm.json/Currency",
      "toEntityAttribute": "RecId"
    },
    {
      "name": "",
      "fromEntity": "PurchPurchaseOrderHeader.cdm.json/PurchPurchaseOrderHeader",
      "fromEntityAttribute": "Relationship_EuroCurrencyRelationshipId",
      "toEntity": "/core/operationsCommon/Tables/Common/Currency/Group/Currency.cdm.json/Currency",
      "toEntityAttribute": "RecId"
    },
    {
      "name": "",
      "fromEntity": "PurchPurchaseOrderHeader.cdm.json/PurchPurchaseOrderHeader",
      "fromEntityAttribute": "Relationship_PurchTableRelationshipId",
      "toEntity": "/core/operationsCommon/Tables/SupplyChain/ProcurementAndSourcing/WorksheetHeader/PurchTable.cdm.json/PurchTable",
      "toEntityAttribute": "RecId"
    },
    {
      "name": "",
      "fromEntity": "PurchPurchaseOrderHeader.cdm.json/PurchPurchaseOrderHeader",
      "fromEntityAttribute": "Relationship_VendPurchOrderJourRelationshipId",
      "toEntity": "/core/operationsCommon/Tables/SupplyChain/ProcurementAndSourcing/Transaction/VendPurchOrderJour.cdm.json/VendPurchOrderJour",
      "toEntityAttribute": "RecId"
    },
    {
      "name": "",
      "fromEntity": "PurchPurchaseOrderHeader.cdm.json/PurchPurchaseOrderHeader",
      "fromEntityAttribute": "Relationship_PaymTermRelationshipId",
      "toEntity": "/core/operationsCommon/Tables/Finance/Bank/Group/PaymTerm.cdm.json/PaymTerm",
      "toEntityAttribute": "RecId"
    },
    {
      "name": "",
      "fromEntity": "PurchPurchaseOrderHeader.cdm.json/PurchPurchaseOrderHeader",
      "fromEntityAttribute": "Relationship_CompanyRelationshipId",
      "toEntity": "/core/operationsCommon/Tables/Finance/Ledger/Main/CompanyInfo.cdm.json/CompanyInfo",
      "toEntityAttribute": "RecId"
    },
    {
      "name": "",
      "fromEntity": "ProcCategoryTmpAccessPolicy.cdm.json/ProcCategoryTmpAccessPolicy",
      "fromEntityAttribute": "Relationship_LegalEntityRelationshipId",
      "toEntity": "/core/operationsCommon/Tables/Finance/Ledger/Main/CompanyInfo.cdm.json/CompanyInfo",
      "toEntityAttribute": "RecId"
    },
    {
      "name": "",
      "fromEntity": "PurchReqTableMyRequisitionsDataSetTable.cdm.json/PurchReqTableMyRequisitionsDataSetTable",
      "fromEntityAttribute": "Relationship_CompanyRelationshipId",
      "toEntity": "/core/operationsCommon/Tables/Finance/Ledger/Main/CompanyInfo.cdm.json/CompanyInfo",
      "toEntityAttribute": "RecId"
    },
    {
      "name": "",
      "fromEntity": "PurchAgreementCertification.cdm.json/PurchAgreementCertification",
      "fromEntityAttribute": "Relationship_PurchAgreementHeaderRelationshipId",
      "toEntity": "/core/operationsCommon/Tables/SupplyChain/ProcurementAndSourcing/WorksheetHeader/PurchAgreementHeader.cdm.json/PurchAgreementHeader",
      "toEntityAttribute": "RecId"
    },
    {
      "name": "",
      "fromEntity": "PurchAgreementCertification.cdm.json/PurchAgreementCertification",
      "fromEntityAttribute": "Relationship_VendCertificationRelationshipId",
      "toEntity": "/core/operationsCommon/Tables/SupplyChain/Vendor/Transaction/VendCertification.cdm.json/VendCertification",
      "toEntityAttribute": "RecId"
    },
    {
      "name": "",
      "fromEntity": "PurchAgreementCertification.cdm.json/PurchAgreementCertification",
      "fromEntityAttribute": "Relationship_VendTableRelationshipId",
      "toEntity": "/core/operationsCommon/Tables/SupplyChain/Vendor/Main/VendTable.cdm.json/VendTable",
      "toEntityAttribute": "RecId"
    },
    {
      "name": "",
      "fromEntity": "PurchaseOrderResponseActionRemarks.cdm.json/PurchaseOrderResponseActionRemarks",
      "fromEntityAttribute": "Relationship_LanguageTableRelationshipId",
      "toEntity": "/core/operationsCommon/Tables/System/SystemAdministration/Group/LanguageTable.cdm.json/LanguageTable",
      "toEntityAttribute": "RecId"
    },
    {
      "name": "",
      "fromEntity": "PurchaseOrderResponseActionRemarks.cdm.json/PurchaseOrderResponseActionRemarks",
      "fromEntityAttribute": "Relationship_CompanyRelationshipId",
      "toEntity": "/core/operationsCommon/Tables/Finance/Ledger/Main/CompanyInfo.cdm.json/CompanyInfo",
      "toEntityAttribute": "RecId"
    },
    {
      "name": "",
      "fromEntity": "PurchReceiptsListHeaderTmp.cdm.json/PurchReceiptsListHeaderTmp",
      "fromEntityAttribute": "Relationship_PurchTableRelationshipId",
      "toEntity": "/core/operationsCommon/Tables/SupplyChain/ProcurementAndSourcing/WorksheetHeader/PurchTable.cdm.json/PurchTable",
      "toEntityAttribute": "RecId"
    },
    {
      "name": "",
      "fromEntity": "PurchReceiptsListHeaderTmp.cdm.json/PurchReceiptsListHeaderTmp",
      "fromEntityAttribute": "Relationship_VendReceiptsListJourRelationshipId",
      "toEntity": "/core/operationsCommon/Tables/SupplyChain/ProcurementAndSourcing/Transaction/VendReceiptsListJour.cdm.json/VendReceiptsListJour",
      "toEntityAttribute": "RecId"
    },
    {
      "name": "",
      "fromEntity": "PurchReceiptsListHeaderTmp.cdm.json/PurchReceiptsListHeaderTmp",
      "fromEntityAttribute": "Relationship_CompanyRelationshipId",
      "toEntity": "/core/operationsCommon/Tables/Finance/Ledger/Main/CompanyInfo.cdm.json/CompanyInfo",
      "toEntityAttribute": "RecId"
    },
    {
      "name": "",
      "fromEntity": "PurchRFQPublishLine_PSN.cdm.json/PurchRFQPublishLine_PSN",
      "fromEntityAttribute": "Relationship_CurrencyRelationshipId",
      "toEntity": "/core/operationsCommon/Tables/Common/Currency/Group/Currency.cdm.json/Currency",
      "toEntityAttribute": "RecId"
    },
    {
      "name": "",
      "fromEntity": "PurchRFQPublishLine_PSN.cdm.json/PurchRFQPublishLine_PSN",
      "fromEntityAttribute": "Relationship_EcoResCategoryRelationshipId",
      "toEntity": "/core/operationsCommon/Tables/SupplyChain/ProductInformationManagement/Main/EcoResCategory.cdm.json/EcoResCategory",
      "toEntityAttribute": "RecId"
    },
    {
      "name": "",
      "fromEntity": "PurchRFQPublishLine_PSN.cdm.json/PurchRFQPublishLine_PSN",
      "fromEntityAttribute": "Relationship_InventTableRelationshipId",
      "toEntity": "/core/operationsCommon/Tables/SupplyChain/ProductInformationManagement/Main/InventTable.cdm.json/InventTable",
      "toEntityAttribute": "RecId"
    },
    {
      "name": "",
      "fromEntity": "PurchRFQPublishLine_PSN.cdm.json/PurchRFQPublishLine_PSN",
      "fromEntityAttribute": "Relationship_PurchRFQPublishTable_PSNRelationshipId",
      "toEntity": "/core/operationsCommon/Tables/SupplyChain/ProcurementAndSourcing/WorksheetHeader/PurchRFQPublishTable_PSN.cdm.json/PurchRFQPublishTable_PSN",
      "toEntityAttribute": "RecId"
    },
    {
      "name": "",
      "fromEntity": "PurchRFQPublishLine_PSN.cdm.json/PurchRFQPublishLine_PSN",
      "fromEntityAttribute": "Relationship_CompanyRelationshipId",
      "toEntity": "/core/operationsCommon/Tables/Finance/Ledger/Main/CompanyInfo.cdm.json/CompanyInfo",
      "toEntityAttribute": "RecId"
    },
    {
      "name": "",
      "fromEntity": "/core/operationsCommon/Entities/SupplyChain/ProcurementAndSourcing/PurchPublishedRequestForQuotationLineEntity.cdm.json/PurchPublishedRequestForQuotationLineEntity",
      "fromEntityAttribute": "BackingTable_PurchRFQPublishLine_PSNRelationshipId",
      "toEntity": "PurchRFQPublishLine_PSN.cdm.json/PurchRFQPublishLine_PSN",
      "toEntityAttribute": "RecId"
    },
    {
      "name": "",
      "fromEntity": "PurchRFQCaseTableKMCollection.cdm.json/PurchRFQCaseTableKMCollection",
      "fromEntityAttribute": "Relationship_PurchRFQCaseTableRelationshipId",
      "toEntity": "/core/operationsCommon/Tables/SupplyChain/ProcurementAndSourcing/WorksheetHeader/PurchRFQCaseTable.cdm.json/PurchRFQCaseTable",
      "toEntityAttribute": "RecId"
    },
    {
      "name": "",
      "fromEntity": "PurchRFQCaseTableKMCollection.cdm.json/PurchRFQCaseTableKMCollection",
      "fromEntityAttribute": "Relationship_CompanyRelationshipId",
      "toEntity": "/core/operationsCommon/Tables/Finance/Ledger/Main/CompanyInfo.cdm.json/CompanyInfo",
      "toEntityAttribute": "RecId"
    },
    {
      "name": "",
      "fromEntity": "PurchAgreementSubcontractor.cdm.json/PurchAgreementSubcontractor",
      "fromEntityAttribute": "Relationship_PurchAgreementHeaderRelationshipId",
      "toEntity": "/core/operationsCommon/Tables/SupplyChain/ProcurementAndSourcing/WorksheetHeader/PurchAgreementHeader.cdm.json/PurchAgreementHeader",
      "toEntityAttribute": "RecId"
    },
    {
      "name": "",
      "fromEntity": "PurchAgreementSubcontractor.cdm.json/PurchAgreementSubcontractor",
      "fromEntityAttribute": "Relationship_SubContractorRelationshipId",
      "toEntity": "/core/operationsCommon/Tables/SupplyChain/Vendor/Main/VendTable.cdm.json/VendTable",
      "toEntityAttribute": "RecId"
    },
    {
      "name": "",
      "fromEntity": "PurchAgreementSubcontractor.cdm.json/PurchAgreementSubcontractor",
      "fromEntityAttribute": "Relationship_VendBankAccountRelationshipId",
      "toEntity": "/core/operationsCommon/Tables/SupplyChain/Vendor/Main/VendBankAccount.cdm.json/VendBankAccount",
      "toEntityAttribute": "RecId"
    },
    {
      "name": "",
      "fromEntity": "PurchAgreementSubcontractor.cdm.json/PurchAgreementSubcontractor",
      "fromEntityAttribute": "Relationship_VendTableRelationshipId",
      "toEntity": "/core/operationsCommon/Tables/SupplyChain/Vendor/Main/VendTable.cdm.json/VendTable",
      "toEntityAttribute": "RecId"
    },
    {
      "name": "",
      "fromEntity": "PurchPolicyRuleCatThreshold_PSN.cdm.json/PurchPolicyRuleCatThreshold_PSN",
      "fromEntityAttribute": "Relationship_EcoResCategoryRelationshipId",
      "toEntity": "/core/operationsCommon/Tables/SupplyChain/ProductInformationManagement/Main/EcoResCategory.cdm.json/EcoResCategory",
      "toEntityAttribute": "RecId"
    },
    {
      "name": "",
      "fromEntity": "PurchPolicyRuleCatThreshold_PSN.cdm.json/PurchPolicyRuleCatThreshold_PSN",
      "fromEntityAttribute": "Relationship_SysPolicyRuleRelationshipId",
      "toEntity": "/core/operationsCommon/Tables/System/Workflow/Main/SysPolicyRule.cdm.json/SysPolicyRule",
      "toEntityAttribute": "RecId"
    },
    {
      "name": "",
      "fromEntity": "PurchPolicyRuleCatThresholdDetail_PSN.cdm.json/PurchPolicyRuleCatThresholdDetail_PSN",
      "fromEntityAttribute": "Relationship_PurchPolicyRuleCatThresholdRelationshipId",
      "toEntity": "PurchPolicyRuleCatThreshold_PSN.cdm.json/PurchPolicyRuleCatThreshold_PSN",
      "toEntityAttribute": "RecId"
    },
    {
      "name": "",
      "fromEntity": "PurchReApprovalPolicyRuleFields.cdm.json/PurchReApprovalPolicyRuleFields",
      "fromEntityAttribute": "Relationship_PurchReApprovalPolicyRuleTableRelationshipId",
      "toEntity": "/core/operationsCommon/Tables/SupplyChain/ProcurementAndSourcing/Main/PurchReApprovalPolicyRuleTable.cdm.json/PurchReApprovalPolicyRuleTable",
      "toEntityAttribute": "RecId"
    },
    {
      "name": "",
      "fromEntity": "PurchRFQSolicitationType.cdm.json/PurchRFQSolicitationType",
      "fromEntityAttribute": "Relationship_DefaultScoringMethodRelationshipId",
      "toEntity": "/core/operationsCommon/Tables/SupplyChain/ProcurementAndSourcing/Main/PurchRFQScoringMethod.cdm.json/PurchRFQScoringMethod",
      "toEntityAttribute": "RecId"
    },
    {
      "name": "",
      "fromEntity": "PurchRFQSolicitationType.cdm.json/PurchRFQSolicitationType",
      "fromEntityAttribute": "Relationship_PurchRFQCloseVisibilityTypeRelationshipId",
      "toEntity": "PurchRFQCloseVisibilityType_PSN.cdm.json/PurchRFQCloseVisibilityType_PSN",
      "toEntityAttribute": "RecId"
    },
    {
      "name": "",
      "fromEntity": "PurchRFQSolicitationType.cdm.json/PurchRFQSolicitationType",
      "fromEntityAttribute": "Relationship_CompanyRelationshipId",
      "toEntity": "/core/operationsCommon/Tables/Finance/Ledger/Main/CompanyInfo.cdm.json/CompanyInfo",
      "toEntityAttribute": "RecId"
    },
    {
      "name": "",
      "fromEntity": "/core/operationsCommon/Tables/SupplyChain/ProcurementAndSourcing/WorksheetHeader/PurchRFQCaseTable.cdm.json/PurchRFQCaseTable",
      "fromEntityAttribute": "Relationship_PurchRFQSolicitationTypeRelationshipId",
      "toEntity": "PurchRFQSolicitationType.cdm.json/PurchRFQSolicitationType",
      "toEntityAttribute": "RecId"
    },
    {
      "name": "",
      "fromEntity": "/core/operationsCommon/Tables/SupplyChain/ProcurementAndSourcing/WorksheetHeader/PurchRFQTable.cdm.json/PurchRFQTable",
      "fromEntityAttribute": "Relationship_PurchRFQSolicitationTypeRelationshipId",
      "toEntity": "PurchRFQSolicitationType.cdm.json/PurchRFQSolicitationType",
      "toEntityAttribute": "RecId"
    },
    {
      "name": "",
      "fromEntity": "/core/operationsCommon/Tables/SupplyChain/ProcurementAndSourcing/Parameter/PurchRFQParameters.cdm.json/PurchRFQParameters",
      "fromEntityAttribute": "Relationship_PurchRFQSolicitationTypeRelationshipId",
      "toEntity": "PurchRFQSolicitationType.cdm.json/PurchRFQSolicitationType",
      "toEntityAttribute": "RecId"
    },
    {
      "name": "",
      "fromEntity": "PSNPurchRFQSolicitationBiddingItem.cdm.json/PSNPurchRFQSolicitationBiddingItem",
      "fromEntityAttribute": "Relationship_SolicitationTypeRelationshipId",
      "toEntity": "PurchRFQSolicitationType.cdm.json/PurchRFQSolicitationType",
      "toEntityAttribute": "RecId"
    },
    {
      "name": "",
      "fromEntity": "/core/operationsCommon/Entities/SupplyChain/ProcurementAndSourcing/PurchRequestForQuotationSolicitationTypeEntity.cdm.json/PurchRequestForQuotationSolicitationTypeEntity",
      "fromEntityAttribute": "BackingTable_PurchRFQSolicitationTypeRelationshipId",
      "toEntity": "PurchRFQSolicitationType.cdm.json/PurchRFQSolicitationType",
      "toEntityAttribute": "RecId"
    },
    {
      "name": "",
      "fromEntity": "PurchRFQTableKMCollection.cdm.json/PurchRFQTableKMCollection",
      "fromEntityAttribute": "Relationship_PurchRFQTableRelationshipId",
      "toEntity": "/core/operationsCommon/Tables/SupplyChain/ProcurementAndSourcing/WorksheetHeader/PurchRFQTable.cdm.json/PurchRFQTable",
      "toEntityAttribute": "RecId"
    },
    {
      "name": "",
      "fromEntity": "PurchRFQTableKMCollection.cdm.json/PurchRFQTableKMCollection",
      "fromEntityAttribute": "Relationship_CompanyRelationshipId",
      "toEntity": "/core/operationsCommon/Tables/Finance/Ledger/Main/CompanyInfo.cdm.json/CompanyInfo",
      "toEntityAttribute": "RecId"
    },
    {
      "name": "",
      "fromEntity": "PurchRFQTableQuestionnaireResponse.cdm.json/PurchRFQTableQuestionnaireResponse",
      "fromEntityAttribute": "Relationship_PurchRFQTableKMCollectionRelationshipId",
      "toEntity": "PurchRFQTableKMCollection.cdm.json/PurchRFQTableKMCollection",
      "toEntityAttribute": "RecId"
    },
    {
      "name": "",
      "fromEntity": "/core/operationsCommon/Entities/SupplyChain/ProcurementAndSourcing/PurchRequestForQuotationReplyQuestionnaireEntity.cdm.json/PurchRequestForQuotationReplyQuestionnaireEntity",
      "fromEntityAttribute": "BackingTable_PurchRFQTableKMCollectionRelationshipId",
      "toEntity": "PurchRFQTableKMCollection.cdm.json/PurchRFQTableKMCollection",
      "toEntityAttribute": "RecId"
    },
    {
      "name": "",
      "fromEntity": "PurchPurchaseOrderTmp.cdm.json/PurchPurchaseOrderTmp",
      "fromEntityAttribute": "Relationship_CurrencyRelationshipId",
      "toEntity": "/core/operationsCommon/Tables/Common/Currency/Group/Currency.cdm.json/Currency",
      "toEntityAttribute": "RecId"
    },
    {
      "name": "",
      "fromEntity": "PurchPurchaseOrderTmp.cdm.json/PurchPurchaseOrderTmp",
      "fromEntityAttribute": "Relationship_InventTableRelationshipId",
      "toEntity": "/core/operationsCommon/Tables/SupplyChain/ProductInformationManagement/Main/InventTable.cdm.json/InventTable",
      "toEntityAttribute": "RecId"
    },
    {
      "name": "",
      "fromEntity": "PurchPurchaseOrderTmp.cdm.json/PurchPurchaseOrderTmp",
      "fromEntityAttribute": "Relationship_TaxTableRelationshipId",
      "toEntity": "/core/operationsCommon/Tables/Finance/Tax/Group/TaxTable.cdm.json/TaxTable",
      "toEntityAttribute": "RecId"
    },
    {
      "name": "",
      "fromEntity": "PurchPurchaseOrderTmp.cdm.json/PurchPurchaseOrderTmp",
      "fromEntityAttribute": "Relationship_VendPurchOrderJourRelationshipId",
      "toEntity": "/core/operationsCommon/Tables/SupplyChain/ProcurementAndSourcing/Transaction/VendPurchOrderJour.cdm.json/VendPurchOrderJour",
      "toEntityAttribute": "RecId"
    },
    {
      "name": "",
      "fromEntity": "PurchPurchaseOrderTmp.cdm.json/PurchPurchaseOrderTmp",
      "fromEntityAttribute": "Relationship_PurchLineRelationshipId",
      "toEntity": "/core/operationsCommon/Tables/SupplyChain/ProcurementAndSourcing/WorksheetLine/PurchLine.cdm.json/PurchLine",
      "toEntityAttribute": "RecId"
    },
    {
      "name": "",
      "fromEntity": "PurchPurchaseOrderTmp.cdm.json/PurchPurchaseOrderTmp",
      "fromEntityAttribute": "Relationship_CompanyRelationshipId",
      "toEntity": "/core/operationsCommon/Tables/Finance/Ledger/Main/CompanyInfo.cdm.json/CompanyInfo",
      "toEntityAttribute": "RecId"
    },
    {
      "name": "",
      "fromEntity": "VendRFQAmendmentJour.cdm.json/VendRFQAmendmentJour",
      "fromEntityAttribute": "Relationship_RelationForeignKey1RelationshipId",
      "toEntity": "/core/operationsCommon/Tables/SupplyChain/ProcurementAndSourcing/Transaction/VendRFQJour.cdm.json/VendRFQJour",
      "toEntityAttribute": "RecId"
    },
    {
      "name": "",
      "fromEntity": "VendRFQAmendmentJour.cdm.json/VendRFQAmendmentJour",
      "fromEntityAttribute": "Relationship_CompanyRelationshipId",
      "toEntity": "/core/operationsCommon/Tables/Finance/Ledger/Main/CompanyInfo.cdm.json/CompanyInfo",
      "toEntityAttribute": "RecId"
    },
    {
      "name": "",
      "fromEntity": "PurchRFQTableQuestionnaireResponse.cdm.json/PurchRFQTableQuestionnaireResponse",
      "fromEntityAttribute": "Relationship_CompanyRelationshipId",
      "toEntity": "/core/operationsCommon/Tables/Finance/Ledger/Main/CompanyInfo.cdm.json/CompanyInfo",
      "toEntityAttribute": "RecId"
    },
    {
      "name": "",
      "fromEntity": "PurchRFQReplyScoringStatus.cdm.json/PurchRFQReplyScoringStatus",
      "fromEntityAttribute": "Relationship_PurchRFQReplyStatusRelationshipId",
      "toEntity": "/core/operationsCommon/Tables/SupplyChain/ProcurementAndSourcing/Main/PurchRFQReplyStatus.cdm.json/PurchRFQReplyStatus",
      "toEntityAttribute": "RecId"
    },
    {
      "name": "",
      "fromEntity": "PurchRFQReplyScoringStatus.cdm.json/PurchRFQReplyScoringStatus",
      "fromEntityAttribute": "Relationship_PurchRFQReplyTableRelationshipId",
      "toEntity": "/core/operationsCommon/Tables/SupplyChain/ProcurementAndSourcing/WorksheetHeader/PurchRFQReplyTable.cdm.json/PurchRFQReplyTable",
      "toEntityAttribute": "RecId"
    },
    {
      "name": "",
      "fromEntity": "PurchRFQReplyScoringStatus.cdm.json/PurchRFQReplyScoringStatus",
      "fromEntityAttribute": "Relationship_CompanyRelationshipId",
      "toEntity": "/core/operationsCommon/Tables/Finance/Ledger/Main/CompanyInfo.cdm.json/CompanyInfo",
      "toEntityAttribute": "RecId"
    },
    {
      "name": "",
      "fromEntity": "PurchRFQCloseVisibilityType_PSN.cdm.json/PurchRFQCloseVisibilityType_PSN",
      "fromEntityAttribute": "Relationship_CompanyRelationshipId",
      "toEntity": "/core/operationsCommon/Tables/Finance/Ledger/Main/CompanyInfo.cdm.json/CompanyInfo",
      "toEntityAttribute": "RecId"
    },
    {
      "name": "",
      "fromEntity": "/core/operationsCommon/Tables/SupplyChain/ProcurementAndSourcing/WorksheetHeader/PurchRFQCaseTable.cdm.json/PurchRFQCaseTable",
      "fromEntityAttribute": "Relationship_PurchRFQCloseVisibilityTypeRelationshipId",
      "toEntity": "PurchRFQCloseVisibilityType_PSN.cdm.json/PurchRFQCloseVisibilityType_PSN",
      "toEntityAttribute": "RecId"
    },
    {
      "name": "",
      "fromEntity": "/core/operationsCommon/Tables/SupplyChain/ProcurementAndSourcing/Parameter/PurchRFQParameters.cdm.json/PurchRFQParameters",
      "fromEntityAttribute": "Relationship_PurchRFQCloseVisibilityTypeRelationshipId",
      "toEntity": "PurchRFQCloseVisibilityType_PSN.cdm.json/PurchRFQCloseVisibilityType_PSN",
      "toEntityAttribute": "RecId"
    },
    {
      "name": "",
      "fromEntity": "PurchReqTableHistoryTotals.cdm.json/PurchReqTableHistoryTotals",
      "fromEntityAttribute": "Relationship_CurrencyCodeRelationshipId",
      "toEntity": "/core/operationsCommon/Tables/Common/Currency/Group/Currency.cdm.json/Currency",
      "toEntityAttribute": "RecId"
    },
    {
      "name": "",
      "fromEntity": "PurchReqTableHistoryTotals.cdm.json/PurchReqTableHistoryTotals",
      "fromEntityAttribute": "Relationship_PurchReqTableHistoryRelationshipId",
      "toEntity": "/core/operationsCommon/Tables/SupplyChain/ProcurementAndSourcing/TransactionHeader/PurchReqTableHistory.cdm.json/PurchReqTableHistory",
      "toEntityAttribute": "RecId"
    },
    {
      "name": "",
      "fromEntity": "PurchAgreementFinDimensionAccess_PSN.cdm.json/PurchAgreementFinDimensionAccess_PSN",
      "fromEntityAttribute": "Relationship_DimensionAttributeValueRelationshipId",
      "toEntity": "/core/operationsCommon/Tables/Finance/FinancialDimensions/Main/DimensionAttributeValue.cdm.json/DimensionAttributeValue",
      "toEntityAttribute": "RecId"
    },
    {
      "name": "",
      "fromEntity": "PurchAgreementFinDimensionAccess_PSN.cdm.json/PurchAgreementFinDimensionAccess_PSN",
      "fromEntityAttribute": "Relationship_PurchAgreementHeaderRelationshipId",
      "toEntity": "/core/operationsCommon/Tables/SupplyChain/ProcurementAndSourcing/WorksheetHeader/PurchAgreementHeader.cdm.json/PurchAgreementHeader",
      "toEntityAttribute": "RecId"
    },
    {
      "name": "",
      "fromEntity": "PurchAgreementFinDimensionAccess_PSN.cdm.json/PurchAgreementFinDimensionAccess_PSN",
      "fromEntityAttribute": "Relationship_CompanyRelationshipId",
      "toEntity": "/core/operationsCommon/Tables/Finance/Ledger/Main/CompanyInfo.cdm.json/CompanyInfo",
      "toEntityAttribute": "RecId"
    },
    {
      "name": "",
      "fromEntity": "PurchPolicyRuleCatThresholdDetail_PSN.cdm.json/PurchPolicyRuleCatThresholdDetail_PSN",
      "fromEntityAttribute": "Relationship_CompanyRelationshipId",
      "toEntity": "/core/operationsCommon/Tables/Finance/Ledger/Main/CompanyInfo.cdm.json/CompanyInfo",
      "toEntityAttribute": "RecId"
    },
    {
      "name": "",
      "fromEntity": "AifPortValueMap.cdm.json/AifPortValueMap",
      "fromEntityAttribute": "Relationship_AgreementClassificationExtCodeRelationshipId",
      "toEntity": "/core/operationsCommon/Tables/SupplyChain/ProcurementAndSourcing/Group/ExtCodeTable.cdm.json/ExtCodeTable",
      "toEntityAttribute": "RecId"
    },
    {
      "name": "",
      "fromEntity": "AifPortValueMap.cdm.json/AifPortValueMap",
      "fromEntityAttribute": "Relationship_BarCodeSetupRelationshipId",
      "toEntity": "/core/operationsCommon/Tables/SupplyChain/Inventory/Group/BarcodeSetup.cdm.json/BarcodeSetup",
      "toEntityAttribute": "RecId"
    },
    {
      "name": "",
      "fromEntity": "AifPortValueMap.cdm.json/AifPortValueMap",
      "fromEntityAttribute": "Relationship_CountryRegionExtCodeRelationshipId",
      "toEntity": "/core/operationsCommon/Tables/SupplyChain/ProcurementAndSourcing/Group/ExtCodeTable.cdm.json/ExtCodeTable",
      "toEntityAttribute": "RecId"
    },
    {
      "name": "",
      "fromEntity": "AifPortValueMap.cdm.json/AifPortValueMap",
      "fromEntityAttribute": "Relationship_CountyExtCodeRelationshipId",
      "toEntity": "/core/operationsCommon/Tables/SupplyChain/ProcurementAndSourcing/Group/ExtCodeTable.cdm.json/ExtCodeTable",
      "toEntityAttribute": "RecId"
    },
    {
      "name": "",
      "fromEntity": "AifPortValueMap.cdm.json/AifPortValueMap",
      "fromEntityAttribute": "Relationship_CustAccountExtCodeRelationshipId",
      "toEntity": "/core/operationsCommon/Tables/SupplyChain/ProcurementAndSourcing/Group/ExtCodeTable.cdm.json/ExtCodeTable",
      "toEntityAttribute": "RecId"
    },
    {
      "name": "",
      "fromEntity": "AifPortValueMap.cdm.json/AifPortValueMap",
      "fromEntityAttribute": "Relationship_DlvModeExtCodeRelationshipId",
      "toEntity": "/core/operationsCommon/Tables/SupplyChain/ProcurementAndSourcing/Group/ExtCodeTable.cdm.json/ExtCodeTable",
      "toEntityAttribute": "RecId"
    },
    {
      "name": "",
      "fromEntity": "AifPortValueMap.cdm.json/AifPortValueMap",
      "fromEntityAttribute": "Relationship_DlvTermExtCodeRelationshipId",
      "toEntity": "/core/operationsCommon/Tables/SupplyChain/ProcurementAndSourcing/Group/ExtCodeTable.cdm.json/ExtCodeTable",
      "toEntityAttribute": "RecId"
    },
    {
      "name": "",
      "fromEntity": "AifPortValueMap.cdm.json/AifPortValueMap",
      "fromEntityAttribute": "Relationship_InventLocationExtCodeRelationshipId",
      "toEntity": "/core/operationsCommon/Tables/SupplyChain/ProcurementAndSourcing/Group/ExtCodeTable.cdm.json/ExtCodeTable",
      "toEntityAttribute": "RecId"
    },
    {
      "name": "",
      "fromEntity": "AifPortValueMap.cdm.json/AifPortValueMap",
      "fromEntityAttribute": "Relationship_ItemExtCodeRelationshipId",
      "toEntity": "/core/operationsCommon/Tables/SupplyChain/ProcurementAndSourcing/Group/ExtCodeTable.cdm.json/ExtCodeTable",
      "toEntityAttribute": "RecId"
    },
    {
      "name": "",
      "fromEntity": "AifPortValueMap.cdm.json/AifPortValueMap",
      "fromEntityAttribute": "Relationship_MarkupExtCodeRelationshipId",
      "toEntity": "/core/operationsCommon/Tables/SupplyChain/ProcurementAndSourcing/Group/ExtCodeTable.cdm.json/ExtCodeTable",
      "toEntityAttribute": "RecId"
    },
    {
      "name": "",
      "fromEntity": "AifPortValueMap.cdm.json/AifPortValueMap",
      "fromEntityAttribute": "Relationship_ReturnDispCodeExtCodeRelationshipId",
      "toEntity": "/core/operationsCommon/Tables/SupplyChain/ProcurementAndSourcing/Group/ExtCodeTable.cdm.json/ExtCodeTable",
      "toEntityAttribute": "RecId"
    },
    {
      "name": "",
      "fromEntity": "AifPortValueMap.cdm.json/AifPortValueMap",
      "fromEntityAttribute": "Relationship_ReturnReasonCodeExtCodeRelationshipId",
      "toEntity": "/core/operationsCommon/Tables/SupplyChain/ProcurementAndSourcing/Group/ExtCodeTable.cdm.json/ExtCodeTable",
      "toEntityAttribute": "RecId"
    },
    {
      "name": "",
      "fromEntity": "AifPortValueMap.cdm.json/AifPortValueMap",
      "fromEntityAttribute": "Relationship_StateExtCodeRelationshipId",
      "toEntity": "/core/operationsCommon/Tables/SupplyChain/ProcurementAndSourcing/Group/ExtCodeTable.cdm.json/ExtCodeTable",
      "toEntityAttribute": "RecId"
    },
    {
      "name": "",
      "fromEntity": "AifPortValueMap.cdm.json/AifPortValueMap",
      "fromEntityAttribute": "Relationship_TaxExtCodeRelationshipId",
      "toEntity": "/core/operationsCommon/Tables/SupplyChain/ProcurementAndSourcing/Group/ExtCodeTable.cdm.json/ExtCodeTable",
      "toEntityAttribute": "RecId"
    },
    {
      "name": "",
      "fromEntity": "AifPortValueMap.cdm.json/AifPortValueMap",
      "fromEntityAttribute": "Relationship_UnitExtCodeRelationshipId",
      "toEntity": "/core/operationsCommon/Tables/SupplyChain/ProcurementAndSourcing/Group/ExtCodeTable.cdm.json/ExtCodeTable",
      "toEntityAttribute": "RecId"
    },
    {
      "name": "",
      "fromEntity": "AifPortValueMap.cdm.json/AifPortValueMap",
      "fromEntityAttribute": "Relationship_VendAccountExtCodeRelationshipId",
      "toEntity": "/core/operationsCommon/Tables/SupplyChain/ProcurementAndSourcing/Group/ExtCodeTable.cdm.json/ExtCodeTable",
      "toEntityAttribute": "RecId"
    },
    {
      "name": "",
      "fromEntity": "AifPortValueMap.cdm.json/AifPortValueMap",
      "fromEntityAttribute": "Relationship_ZipCodeExtCodeRelationshipId",
      "toEntity": "/core/operationsCommon/Tables/SupplyChain/ProcurementAndSourcing/Group/ExtCodeTable.cdm.json/ExtCodeTable",
      "toEntityAttribute": "RecId"
    },
    {
      "name": "",
      "fromEntity": "PurchReceiptsListDetailsTmp.cdm.json/PurchReceiptsListDetailsTmp",
      "fromEntityAttribute": "Relationship_InventTableRelationshipId",
      "toEntity": "/core/operationsCommon/Tables/SupplyChain/ProductInformationManagement/Main/InventTable.cdm.json/InventTable",
      "toEntityAttribute": "RecId"
    },
    {
      "name": "",
      "fromEntity": "PurchReceiptsListDetailsTmp.cdm.json/PurchReceiptsListDetailsTmp",
      "fromEntityAttribute": "Relationship_VendReceiptsListJourRelationshipId",
      "toEntity": "/core/operationsCommon/Tables/SupplyChain/ProcurementAndSourcing/Transaction/VendReceiptsListJour.cdm.json/VendReceiptsListJour",
      "toEntityAttribute": "RecId"
    },
    {
      "name": "",
      "fromEntity": "PurchReceiptsListDetailsTmp.cdm.json/PurchReceiptsListDetailsTmp",
      "fromEntityAttribute": "Relationship_VendReceiptsListTransRelationshipId",
      "toEntity": "/core/operationsCommon/Tables/SupplyChain/ProcurementAndSourcing/Transaction/VendReceiptsListTrans.cdm.json/VendReceiptsListTrans",
      "toEntityAttribute": "RecId"
    },
    {
      "name": "",
      "fromEntity": "PurchReceiptsListDetailsTmp.cdm.json/PurchReceiptsListDetailsTmp",
      "fromEntityAttribute": "Relationship_CompanyRelationshipId",
      "toEntity": "/core/operationsCommon/Tables/Finance/Ledger/Main/CompanyInfo.cdm.json/CompanyInfo",
      "toEntityAttribute": "RecId"
    },
    {
      "name": "",
      "fromEntity": "PSNPurchRFQSolicitationBiddingItem.cdm.json/PSNPurchRFQSolicitationBiddingItem",
      "fromEntityAttribute": "Relationship_BiddingGuidanceItemRelationshipId",
      "toEntity": "PSNPurchRFQBiddingGuidanceItem.cdm.json/PSNPurchRFQBiddingGuidanceItem",
      "toEntityAttribute": "RecId"
    },
    {
      "name": "",
      "fromEntity": "PSNPurchRFQSolicitationBiddingItem.cdm.json/PSNPurchRFQSolicitationBiddingItem",
      "fromEntityAttribute": "Relationship_CompanyRelationshipId",
      "toEntity": "/core/operationsCommon/Tables/Finance/Ledger/Main/CompanyInfo.cdm.json/CompanyInfo",
      "toEntityAttribute": "RecId"
    },
    {
      "name": "",
      "fromEntity": "PSNPurchRFQBiddingGuidanceItem.cdm.json/PSNPurchRFQBiddingGuidanceItem",
      "fromEntityAttribute": "Relationship_CompanyRelationshipId",
      "toEntity": "/core/operationsCommon/Tables/Finance/Ledger/Main/CompanyInfo.cdm.json/CompanyInfo",
      "toEntityAttribute": "RecId"
    },
    {
      "name": "",
      "fromEntity": "PSNPurchRFQCaseBiddingGuidanceItem.cdm.json/PSNPurchRFQCaseBiddingGuidanceItem",
      "fromEntityAttribute": "Relationship_BiddingGuidanceItemRelationshipId",
      "toEntity": "PSNPurchRFQBiddingGuidanceItem.cdm.json/PSNPurchRFQBiddingGuidanceItem",
      "toEntityAttribute": "RecId"
    },
    {
      "name": "",
      "fromEntity": "PSNPurchRFQCaseBiddingGuidanceItem.cdm.json/PSNPurchRFQCaseBiddingGuidanceItem",
      "fromEntityAttribute": "Relationship_RFQCaseRelationshipId",
      "toEntity": "/core/operationsCommon/Tables/SupplyChain/ProcurementAndSourcing/WorksheetHeader/PurchRFQCaseTable.cdm.json/PurchRFQCaseTable",
      "toEntityAttribute": "RecId"
    },
    {
      "name": "",
      "fromEntity": "PSNPurchRFQCaseBiddingGuidanceItem.cdm.json/PSNPurchRFQCaseBiddingGuidanceItem",
      "fromEntityAttribute": "Relationship_CompanyRelationshipId",
      "toEntity": "/core/operationsCommon/Tables/Finance/Ledger/Main/CompanyInfo.cdm.json/CompanyInfo",
      "toEntityAttribute": "RecId"
    }
  ]
}