{
  "documentVersion": "1.2",
  "jsonSchemaSemanticVersion": "1.0.0",
  "imports": [
    {
      "corpusPath": "cdm:/foundations.4.4.cdm.json"
    },
    {
      "corpusPath": "/core/operationsCommon/Common.1.1.cdm.json",
      "moniker": "base_Common"
    },
    {
      "corpusPath": "/core/operationsCommon/DataEntityView.1.0.1.cdm.json",
      "moniker": "base_DataEntityView"
    },
    {
      "corpusPath": "/core/operationsCommon/Tables/Finance/FixedAssets/Main/AssetBook.1.2.cdm.json"
    },
    {
      "corpusPath": "/core/operationsCommon/Tables/Finance/FixedAssets/WorksheetHeader/AssetDocumentTable_JP.1.2.cdm.json"
    },
    {
      "corpusPath": "/core/operationsCommon/Tables/Finance/FixedAssets/Main/AssetTable.1.2.cdm.json"
    },
    {
      "corpusPath": "/core/operationsCommon/Tables/Finance/Ledger/Main/CompanyInfo.1.2.cdm.json"
    }
  ],
  "definitions": [
    {
      "entityName": "AssetDocumentEntry_JP",
      "extendsEntity": "base_Common/Common",
      "exhibitsTraits": [
        {
          "traitReference": "is.CDM.entityVersion",
          "arguments": [
            {
              "name": "versionNumber",
              "value": "1.2"
            }
          ]
        }
      ],
      "hasAttributes": [
        {
          "name": "AssetDocumentTable_JP",
          "dataType": "RefRecId",
          "description": ""
        },
        {
          "name": "AssetId",
          "dataType": "AssetId",
          "description": ""
        },
        {
          "name": "BookId",
          "dataType": "AssetBookMergeId",
          "description": ""
        },
        {
          "name": "DataAreaId",
          "dataType": "string",
          "isReadOnly": true
        },
        {
          "entity": {
            "entityReference": "AssetBook"
          },
          "name": "Relationship_AssetBookRelationship",
          "resolutionGuidance": {
            "entityByReference": {
              "allowReference": true
            }
          }
        },
        {
          "entity": {
            "entityReference": "AssetDocumentTable_JP"
          },
          "name": "Relationship_AssetDocumentTable_JPRelationship",
          "resolutionGuidance": {
            "entityByReference": {
              "allowReference": true
            }
          }
        },
        {
          "entity": {
            "entityReference": "AssetTable"
          },
          "name": "Relationship_AssetTable_AssetIdRelationship",
          "resolutionGuidance": {
            "entityByReference": {
              "allowReference": true
            }
          }
        },
        {
          "entity": {
            "entityReference": "CompanyInfo"
          },
          "name": "Relationship_CompanyRelationship",
          "resolutionGuidance": {
            "entityByReference": {
              "allowReference": true
            }
          }
        }
      ],
      "displayName": "Fixed asset document entry"
    },
    {
      "dataTypeName": "RefRecId",
      "extendsDataType": "bigInteger"
    },
    {
      "dataTypeName": "AssetId",
      "extendsDataType": "string"
    },
    {
      "dataTypeName": "AssetBookMergeId",
      "extendsDataType": "string"
    }
  ]
}