{
  "documentVersion": "1.1.1",
  "jsonSchemaSemanticVersion": "1.0.0",
  "imports": [
    {
      "corpusPath": "cdm:/foundations.cdm.json"
    },
    {
      "corpusPath": "/core/operationsCommon/Common.cdm.json",
      "moniker": "base_Common"
    },
    {
      "corpusPath": "/core/operationsCommon/DataEntityView.cdm.json",
      "moniker": "base_DataEntityView"
    },
    {
      "corpusPath": "/core/operationsCommon/Tables/SupplyChain/SalesAndMarketing/Parameter/CustFormletterParameters.cdm.json"
    },
    {
      "corpusPath": "/core/operationsCommon/Tables/Finance/Ledger/Main/CompanyInfo.cdm.json"
    }
  ],
  "definitions": [
    {
      "entityName": "SalesFormletterSalesAgreementFormPrintingConfigurationEntity",
      "extendsEntity": "base_DataEntityView/DataEntityView",
      "exhibitsTraits": [
        {
          "traitReference": "is.CDM.entityVersion",
          "arguments": [
            {
              "name": "versionNumber",
              "value": "1.1.1"
            }
          ]
        }
      ],
      "hasAttributes": [
        {
          "name": "IsProductColorIdDisplayed",
          "dataType": "string",
          "isNullable": true,
          "description": ""
        },
        {
          "name": "IsProductConfigurationIdDisplayed",
          "dataType": "string",
          "isNullable": true,
          "description": ""
        },
        {
          "name": "IsProductSizeIdDisplayed",
          "dataType": "string",
          "isNullable": true,
          "description": ""
        },
        {
          "name": "IsProductStyleIdDisplayed",
          "dataType": "string",
          "isNullable": true,
          "description": ""
        },
        {
          "name": "IsProductVersionIdDisplayed",
          "dataType": "string",
          "isNullable": true,
          "description": ""
        },
        {
          "name": "IsShippingSiteIdDisplayed",
          "dataType": "string",
          "isNullable": true,
          "description": ""
        },
        {
          "name": "IsShippingWarehouseIdDisplayed",
          "dataType": "string",
          "isNullable": true,
          "description": ""
        },
        {
          "name": "InventDimSalesAgreement",
          "dataType": "string",
          "isNullable": true,
          "description": ""
        },
        {
          "name": "PaperFormat",
          "dataType": "string",
          "isNullable": true,
          "description": ""
        },
        {
          "name": "DocumentAttachmentDisplayRule",
          "dataType": "string",
          "isNullable": true,
          "description": ""
        },
        {
          "name": "DisplayedDocumentAttachmentTypeCode",
          "dataType": "string",
          "isNullable": true,
          "description": ""
        },
        {
          "name": "IsAgreementClassificationDisplayed",
          "dataType": "string",
          "isNullable": true,
          "description": ""
        },
        {
          "name": "IsCashDiscountDisplayed",
          "dataType": "string",
          "isNullable": true,
          "description": ""
        },
        {
          "name": "IsContractReferenceDisplayed",
          "dataType": "string",
          "isNullable": true,
          "description": ""
        },
        {
          "name": "IsDeliveryTermsDisplayed",
          "dataType": "string",
          "isNullable": true,
          "description": ""
        },
        {
          "name": "IsMaxEnforcedDisplayed",
          "dataType": "string",
          "isNullable": true,
          "description": ""
        },
        {
          "name": "IsDeliveryModeDisplayed",
          "dataType": "string",
          "isNullable": true,
          "description": ""
        },
        {
          "name": "IsPaymentTermsDisplayed",
          "dataType": "string",
          "isNullable": true,
          "description": ""
        },
        {
          "entity": {
            "entityReference": "CustFormletterParameters"
          },
          "name": "BackingTable_CustFormletterParametersRelationship",
          "resolutionGuidance": {
            "entityByReference": {
              "allowReference": true
            }
          }
        },
        {
          "entity": {
            "entityReference": "CompanyInfo"
          },
          "name": "Relationship_PrimaryCompanyContextRelationship",
          "resolutionGuidance": {
            "entityByReference": {
              "allowReference": true
            }
          }
        }
      ],
      "displayName": "Sales agreement form printing configurations"
    }
  ]
}